{
  "id": 102,
  "top": 0,
  "featured": 0,
  "title": "2025.6.4基础化工月报",
  "brief": " 大盘及基础化工板块走势",
  "createdAt": "2025-06-04 15:21:02",
  "updatedAt": "2025-06-12 14:07:42",
  "deletedAt": null,
  "columnId": 1,
  "column": {
    "id": 1,
    "name": "全部研报"
  },
  "detailed_content": {
    "id": 102,
    "top": 0,
    "featured": 0,
    "title": "2025.6.4基础化工月报",
    "brief": " 大盘及基础化工板块走势",
    "content": "<h3><span style=\"color: rgb(0, 0, 0); font-size: 16px;\"><strong>一、市场行情回顾</strong></span></h3><h4><span style=\"color: rgb(0, 0, 0); font-size: 16px;\"><strong>1. 大盘及基础化工板块走势（2025 年 5 月）</strong></span></h4><p><span style=\"color: rgb(0, 0, 0); font-size: 16px;\">· </span><span style=\"color: rgb(0, 0, 0); font-size: 16px;\"><strong>主要指数涨跌幅</strong></span><span style=\"color: rgb(0, 0, 0); font-size: 16px;\">：</span></p><p><span style=\"color: rgb(0, 0, 0); font-size: 16px;\">· 上证指数：+2.09%；深证成指：+1.42%；创业板指：+2.32%；北证 50 指数：+5.83%；同花顺全 A（加权）：+2.37%。</span></p><p><span style=\"color: rgb(0, 0, 0); font-size: 16px;\">· 基础化工指数：+2.12%，在申万一级行业中排名第 19 位。</span></p><p><span style=\"color: rgb(0, 0, 0); font-size: 16px;\">· </span><span style=\"color: rgb(0, 0, 0); font-size: 16px;\"><strong>二级子行业表现</strong></span><span style=\"color: rgb(0, 0, 0); font-size: 16px;\">：</span></p><p><span style=\"color: rgb(0, 0, 0); font-size: 16px;\">· 化学纤维（+7.98%）、农用化工（+3.89%）、塑料及制品（+3.15%）领涨；化学原料（-0.11%）小幅下跌。</span></p><p><span style=\"color: rgb(0, 0, 0); font-size: 16px;\">· </span><span style=\"color: rgb(0, 0, 0); font-size: 16px;\"><strong>三级子行业涨跌幅前五</strong></span><span style=\"color: rgb(0, 0, 0); font-size: 16px;\">：</span></p><p><span style=\"color: rgb(0, 0, 0); font-size: 16px;\">· 涤纶（+19.53%）、农药（+10.97%）、粘胶（+8.55%）、锦纶（+7.11%）、其他塑料制品（+5.85%）。</span></p><p><span style=\"color: rgb(0, 0, 0); font-size: 16px;\">· </span><span style=\"color: rgb(0, 0, 0); font-size: 16px;\"><strong>三级子行业涨跌幅后五</strong></span><span style=\"color: rgb(0, 0, 0); font-size: 16px;\">：</span></p><p><span style=\"color: rgb(0, 0, 0); font-size: 16px;\">· 碳纤维（-2.65%）、无机盐（-1.94%）、电子化学品（-1.58%）、其他化学原料（-1.39%）、改性塑料（-1.01%）。</span></p><h4><span style=\"color: rgb(0, 0, 0); font-size: 16px;\"><strong>2. 相关公司表现</strong></span></h4><p><span style=\"color: rgb(0, 0, 0); font-size: 16px;\">· </span><span style=\"color: rgb(0, 0, 0); font-size: 16px;\"><strong>个股涨跌幅前十</strong></span><span style=\"color: rgb(0, 0, 0); font-size: 16px;\">：</span></p><p><span style=\"color: rgb(0, 0, 0); font-size: 16px;\">· 苏州龙杰（+84.09%，涤纶）、广康生化（+68.13%，农药）、尤夫股份（+58.49%，涤纶）领涨。</span></p><p><span style=\"color: rgb(0, 0, 0); font-size: 16px;\">· </span><span style=\"color: rgb(0, 0, 0); font-size: 16px;\"><strong>个股涨跌幅后十</strong></span><span style=\"color: rgb(0, 0, 0); font-size: 16px;\">：</span></p><p><span style=\"color: rgb(0, 0, 0); font-size: 16px;\">· 星华新材（-38.13%，非棉纺织品）、亚香股份（-36.98%，食品及饲料添加剂）、福莱新材（-34.69%，其他化学制品 Ⅲ）领跌。</span></p><h3><span style=\"color: rgb(0, 0, 0); font-size: 16px;\"><strong>二、产品涨跌异动</strong></span></h3><h4><span style=\"color: rgb(0, 0, 0); font-size: 16px;\"><strong>1. 涨幅前十产品（2025 年 5 月）</strong></span></h4><table style=\"width: auto;table-layout: fixed;height:2183\"><colgroup contentEditable=\"false\"><col width=90></col><col width=90></col><col width=90></col><col width=90></col><col width=90></col><col width=90></col><col width=90></col><col width=90></col></colgroup><tbody><tr><td colspan=\"1\" rowspan=\"1\" width=\"auto\" style=\"border-width: 1px; border-style: solid; border-color: rgb(204, 204, 204);\"><p style=\"text-align: center;\"><span style=\"font-size: 16px;\"><strong>产品</strong></span></p></td><td colspan=\"1\" rowspan=\"1\" width=\"auto\" style=\"border-width: 1px; border-style: solid; border-color: rgb(204, 204, 204);\"><p style=\"text-align: center;\"><span style=\"font-size: 16px;\"><strong>当前价格</strong></span></p></td><td colspan=\"1\" rowspan=\"1\" width=\"auto\" style=\"border-width: 1px; border-style: solid; border-color: rgb(204, 204, 204);\"><p style=\"text-align: center;\"><span style=\"font-size: 16px;\"><strong>周涨幅</strong></span></p></td><td colspan=\"1\" rowspan=\"1\" width=\"auto\" style=\"border-width: 1px; border-style: solid; border-color: rgb(204, 204, 204);\"><p style=\"text-align: center;\"><span style=\"font-size: 16px;\"><strong>月涨幅</strong></span></p></td><td colspan=\"1\" rowspan=\"1\" width=\"auto\" style=\"border-width: 1px; border-style: solid; border-color: rgb(204, 204, 204);\"><p style=\"text-align: center;\"><span style=\"font-size: 16px;\"><strong>同比</strong></span></p></td><td colspan=\"1\" rowspan=\"1\" width=\"auto\" style=\"border-width: 1px; border-style: solid; border-color: rgb(204, 204, 204);\"><p style=\"text-align: center;\"><span style=\"font-size: 16px;\"><strong>年初至今</strong></span></p></td><td colspan=\"1\" rowspan=\"1\" width=\"auto\" style=\"border-width: 1px; border-style: solid; border-color: rgb(204, 204, 204);\"><p style=\"text-align: center;\"><span style=\"font-size: 16px;\"><strong>单位</strong></span></p></td><td colspan=\"1\" rowspan=\"1\" width=\"auto\" style=\"border-width: 1px; border-style: solid; border-color: rgb(204, 204, 204);\"><p style=\"text-align: center;\"><span style=\"font-size: 16px;\"><strong>市场分析</strong></span></p></td></tr><tr><td colspan=\"1\" rowspan=\"1\" width=\"auto\" style=\"border-width: 1px; border-style: solid; border-color: rgb(204, 204, 204);\"><p style=\"text-align: left;\"><span style=\"font-size: 16px;\">盐酸</span></p></td><td colspan=\"1\" rowspan=\"1\" width=\"auto\" style=\"border-width: 1px; border-style: solid; border-color: rgb(204, 204, 204);\"><p style=\"text-align: left;\"><span style=\"font-size: 16px;\">195</span></p></td><td colspan=\"1\" rowspan=\"1\" width=\"auto\" style=\"border-width: 1px; border-style: solid; border-color: rgb(204, 204, 204);\"><p style=\"text-align: left;\"><span style=\"font-size: 16px;\">35.42%</span></p></td><td colspan=\"1\" rowspan=\"1\" width=\"auto\" style=\"border-width: 1px; border-style: solid; border-color: rgb(204, 204, 204);\"><p style=\"text-align: left;\"><span style=\"font-size: 16px;\">43.38%</span></p></td><td colspan=\"1\" rowspan=\"1\" width=\"auto\" style=\"border-width: 1px; border-style: solid; border-color: rgb(204, 204, 204);\"><p style=\"text-align: left;\"><span style=\"font-size: 16px;\">-3.94%</span></p></td><td colspan=\"1\" rowspan=\"1\" width=\"auto\" style=\"border-width: 1px; border-style: solid; border-color: rgb(204, 204, 204);\"><p style=\"text-align: left;\"><span style=\"font-size: 16px;\">10.80%</span></p></td><td colspan=\"1\" rowspan=\"1\" width=\"auto\" style=\"border-width: 1px; border-style: solid; border-color: rgb(204, 204, 204);\"><p style=\"text-align: left;\"><span style=\"font-size: 16px;\">元 / 吨</span></p></td><td colspan=\"1\" rowspan=\"1\" width=\"auto\" style=\"border-width: 1px; border-style: solid; border-color: rgb(204, 204, 204);\"><p style=\"text-align: left;\"><span style=\"font-size: 16px;\">湖南、福建供应减少，山东供应不稳定，下游需求稳定。</span></p></td></tr><tr><td colspan=\"1\" rowspan=\"1\" width=\"auto\" style=\"border-width: 1px; border-style: solid; border-color: rgb(204, 204, 204);\"><p style=\"text-align: left;\"><span style=\"font-size: 16px;\">氮气</span></p></td><td colspan=\"1\" rowspan=\"1\" width=\"auto\" style=\"border-width: 1px; border-style: solid; border-color: rgb(204, 204, 204);\"><p style=\"text-align: left;\"><span style=\"font-size: 16px;\">511</span></p></td><td colspan=\"1\" rowspan=\"1\" width=\"auto\" style=\"border-width: 1px; border-style: solid; border-color: rgb(204, 204, 204);\"><p style=\"text-align: left;\"><span style=\"font-size: 16px;\">5.36%</span></p></td><td colspan=\"1\" rowspan=\"1\" width=\"auto\" style=\"border-width: 1px; border-style: solid; border-color: rgb(204, 204, 204);\"><p style=\"text-align: left;\"><span style=\"font-size: 16px;\">19.95%</span></p></td><td colspan=\"1\" rowspan=\"1\" width=\"auto\" style=\"border-width: 1px; border-style: solid; border-color: rgb(204, 204, 204);\"><p style=\"text-align: left;\"><span style=\"font-size: 16px;\">9.66%</span></p></td><td colspan=\"1\" rowspan=\"1\" width=\"auto\" style=\"border-width: 1px; border-style: solid; border-color: rgb(204, 204, 204);\"><p style=\"text-align: left;\"><span style=\"font-size: 16px;\">27.11%</span></p></td><td colspan=\"1\" rowspan=\"1\" width=\"auto\" style=\"border-width: 1px; border-style: solid; border-color: rgb(204, 204, 204);\"><p style=\"text-align: left;\"><span style=\"font-size: 16px;\">元 / 吨</span></p></td><td colspan=\"1\" rowspan=\"1\" width=\"auto\" style=\"border-width: 1px; border-style: solid; border-color: rgb(204, 204, 204);\"><p style=\"text-align: left;\"><span style=\"font-size: 16px;\">空分装置检修致供应减少，下游需求增加，市场商谈氛围偏暖。</span></p></td></tr><tr><td colspan=\"1\" rowspan=\"1\" width=\"auto\" style=\"border-width: 1px; border-style: solid; border-color: rgb(204, 204, 204);\"><p style=\"text-align: left;\"><span style=\"font-size: 16px;\">TDI</span></p></td><td colspan=\"1\" rowspan=\"1\" width=\"auto\" style=\"border-width: 1px; border-style: solid; border-color: rgb(204, 204, 204);\"><p style=\"text-align: left;\"><span style=\"font-size: 16px;\">12625</span></p></td><td colspan=\"1\" rowspan=\"1\" width=\"auto\" style=\"border-width: 1px; border-style: solid; border-color: rgb(204, 204, 204);\"><p style=\"text-align: left;\"><span style=\"font-size: 16px;\">3.06%</span></p></td><td colspan=\"1\" rowspan=\"1\" width=\"auto\" style=\"border-width: 1px; border-style: solid; border-color: rgb(204, 204, 204);\"><p style=\"text-align: left;\"><span style=\"font-size: 16px;\">17.10%</span></p></td><td colspan=\"1\" rowspan=\"1\" width=\"auto\" style=\"border-width: 1px; border-style: solid; border-color: rgb(204, 204, 204);\"><p style=\"text-align: left;\"><span style=\"font-size: 16px;\">-13.88%</span></p></td><td colspan=\"1\" rowspan=\"1\" width=\"auto\" style=\"border-width: 1px; border-style: solid; border-color: rgb(204, 204, 204);\"><p style=\"text-align: left;\"><span style=\"font-size: 16px;\">-2.13%</span></p></td><td colspan=\"1\" rowspan=\"1\" width=\"auto\" style=\"border-width: 1px; border-style: solid; border-color: rgb(204, 204, 204);\"><p style=\"text-align: left;\"><span style=\"font-size: 16px;\">元 / 吨</span></p></td><td colspan=\"1\" rowspan=\"1\" width=\"auto\" style=\"border-width: 1px; border-style: solid; border-color: rgb(204, 204, 204);\"><p style=\"text-align: left;\"><span style=\"font-size: 16px;\">工厂控量检修叠加现货收紧，中美关税下调利好，但需求疲软压制成交。</span></p></td></tr><tr><td colspan=\"1\" rowspan=\"1\" width=\"auto\" style=\"border-width: 1px; border-style: solid; border-color: rgb(204, 204, 204);\"><p style=\"text-align: left;\"><span style=\"font-size: 16px;\">溴素</span></p></td><td colspan=\"1\" rowspan=\"1\" width=\"auto\" style=\"border-width: 1px; border-style: solid; border-color: rgb(204, 204, 204);\"><p style=\"text-align: left;\"><span style=\"font-size: 16px;\">24800</span></p></td><td colspan=\"1\" rowspan=\"1\" width=\"auto\" style=\"border-width: 1px; border-style: solid; border-color: rgb(204, 204, 204);\"><p style=\"text-align: left;\"><span style=\"font-size: 16px;\">2.90%</span></p></td><td colspan=\"1\" rowspan=\"1\" width=\"auto\" style=\"border-width: 1px; border-style: solid; border-color: rgb(204, 204, 204);\"><p style=\"text-align: left;\"><span style=\"font-size: 16px;\">12.73%</span></p></td><td colspan=\"1\" rowspan=\"1\" width=\"auto\" style=\"border-width: 1px; border-style: solid; border-color: rgb(204, 204, 204);\"><p style=\"text-align: left;\"><span style=\"font-size: 16px;\">7.83%</span></p></td><td colspan=\"1\" rowspan=\"1\" width=\"auto\" style=\"border-width: 1px; border-style: solid; border-color: rgb(204, 204, 204);\"><p style=\"text-align: left;\"><span style=\"font-size: 16px;\">15.35%</span></p></td><td colspan=\"1\" rowspan=\"1\" width=\"auto\" style=\"border-width: 1px; border-style: solid; border-color: rgb(204, 204, 204);\"><p style=\"text-align: left;\"><span style=\"font-size: 16px;\">元 / 吨</span></p></td><td colspan=\"1\" rowspan=\"1\" width=\"auto\" style=\"border-width: 1px; border-style: solid; border-color: rgb(204, 204, 204);\"><p style=\"text-align: left;\"><span style=\"font-size: 16px;\">山东环保检查致装置降负荷，产量缩减，库存消耗，但下游抵触高价。</span></p></td></tr><tr><td colspan=\"1\" rowspan=\"1\" width=\"auto\" style=\"border-width: 1px; border-style: solid; border-color: rgb(204, 204, 204);\"><p style=\"text-align: left;\"><span style=\"font-size: 16px;\">PX</span></p></td><td colspan=\"1\" rowspan=\"1\" width=\"auto\" style=\"border-width: 1px; border-style: solid; border-color: rgb(204, 204, 204);\"><p style=\"text-align: left;\"><span style=\"font-size: 16px;\">7061.38</span></p></td><td colspan=\"1\" rowspan=\"1\" width=\"auto\" style=\"border-width: 1px; border-style: solid; border-color: rgb(204, 204, 204);\"><p style=\"text-align: left;\"><span style=\"font-size: 16px;\">3.52%</span></p></td><td colspan=\"1\" rowspan=\"1\" width=\"auto\" style=\"border-width: 1px; border-style: solid; border-color: rgb(204, 204, 204);\"><p style=\"text-align: left;\"><span style=\"font-size: 16px;\">12.51%</span></p></td><td colspan=\"1\" rowspan=\"1\" width=\"auto\" style=\"border-width: 1px; border-style: solid; border-color: rgb(204, 204, 204);\"><p style=\"text-align: left;\"><span style=\"font-size: 16px;\">-17.63%</span></p></td><td colspan=\"1\" rowspan=\"1\" width=\"auto\" style=\"border-width: 1px; border-style: solid; border-color: rgb(204, 204, 204);\"><p style=\"text-align: left;\"><span style=\"font-size: 16px;\">1.82%</span></p></td><td colspan=\"1\" rowspan=\"1\" width=\"auto\" style=\"border-width: 1px; border-style: solid; border-color: rgb(204, 204, 204);\"><p style=\"text-align: left;\"><span style=\"font-size: 16px;\">元 / 吨</span></p></td><td colspan=\"1\" rowspan=\"1\" width=\"auto\" style=\"border-width: 1px; border-style: solid; border-color: rgb(204, 204, 204);\"><p style=\"text-align: left;\"><span style=\"font-size: 16px;\">原油上涨支撑成本，PX 开工率 82.82%，PTA 需求高位支撑原料价格。</span></p></td></tr><tr><td colspan=\"1\" rowspan=\"1\" width=\"auto\" style=\"border-width: 1px; border-style: solid; border-color: rgb(204, 204, 204);\"><p style=\"text-align: left;\"><span style=\"font-size: 16px;\">涤纶 FDY</span></p></td><td colspan=\"1\" rowspan=\"1\" width=\"auto\" style=\"border-width: 1px; border-style: solid; border-color: rgb(204, 204, 204);\"><p style=\"text-align: left;\"><span style=\"font-size: 16px;\">7300</span></p></td><td colspan=\"1\" rowspan=\"1\" width=\"auto\" style=\"border-width: 1px; border-style: solid; border-color: rgb(204, 204, 204);\"><p style=\"text-align: left;\"><span style=\"font-size: 16px;\">0.00%</span></p></td><td colspan=\"1\" rowspan=\"1\" width=\"auto\" style=\"border-width: 1px; border-style: solid; border-color: rgb(204, 204, 204);\"><p style=\"text-align: left;\"><span style=\"font-size: 16px;\">11.45%</span></p></td><td colspan=\"1\" rowspan=\"1\" width=\"auto\" style=\"border-width: 1px; border-style: solid; border-color: rgb(204, 204, 204);\"><p style=\"text-align: left;\"><span style=\"font-size: 16px;\">-10.98%</span></p></td><td colspan=\"1\" rowspan=\"1\" width=\"auto\" style=\"border-width: 1px; border-style: solid; border-color: rgb(204, 204, 204);\"><p style=\"text-align: left;\"><span style=\"font-size: 16px;\">-2.67%</span></p></td><td colspan=\"1\" rowspan=\"1\" width=\"auto\" style=\"border-width: 1px; border-style: solid; border-color: rgb(204, 204, 204);\"><p style=\"text-align: left;\"><span style=\"font-size: 16px;\">元 / 吨</span></p></td><td colspan=\"1\" rowspan=\"1\" width=\"auto\" style=\"border-width: 1px; border-style: solid; border-color: rgb(204, 204, 204);\"><p style=\"text-align: left;\"><span style=\"font-size: 16px;\">行业开工率 90.38%，下游织企集中补货，关税缓和刺激订单释放。</span></p></td></tr><tr><td colspan=\"1\" rowspan=\"1\" width=\"auto\" style=\"border-width: 1px; border-style: solid; border-color: rgb(204, 204, 204);\"><p style=\"text-align: left;\"><span style=\"font-size: 16px;\">煤焦油</span></p></td><td colspan=\"1\" rowspan=\"1\" width=\"auto\" style=\"border-width: 1px; border-style: solid; border-color: rgb(204, 204, 204);\"><p style=\"text-align: left;\"><span style=\"font-size: 16px;\">3379</span></p></td><td colspan=\"1\" rowspan=\"1\" width=\"auto\" style=\"border-width: 1px; border-style: solid; border-color: rgb(204, 204, 204);\"><p style=\"text-align: left;\"><span style=\"font-size: 16px;\">0.12%</span></p></td><td colspan=\"1\" rowspan=\"1\" width=\"auto\" style=\"border-width: 1px; border-style: solid; border-color: rgb(204, 204, 204);\"><p style=\"text-align: left;\"><span style=\"font-size: 16px;\">9.92%</span></p></td><td colspan=\"1\" rowspan=\"1\" width=\"auto\" style=\"border-width: 1px; border-style: solid; border-color: rgb(204, 204, 204);\"><p style=\"text-align: left;\"><span style=\"font-size: 16px;\">-20.68%</span></p></td><td colspan=\"1\" rowspan=\"1\" width=\"auto\" style=\"border-width: 1px; border-style: solid; border-color: rgb(204, 204, 204);\"><p style=\"text-align: left;\"><span style=\"font-size: 16px;\">5.49%</span></p></td><td colspan=\"1\" rowspan=\"1\" width=\"auto\" style=\"border-width: 1px; border-style: solid; border-color: rgb(204, 204, 204);\"><p style=\"text-align: left;\"><span style=\"font-size: 16px;\">元 / 吨</span></p></td><td colspan=\"1\" rowspan=\"1\" width=\"auto\" style=\"border-width: 1px; border-style: solid; border-color: rgb(204, 204, 204);\"><p style=\"text-align: left;\"><span style=\"font-size: 16px;\">焦化开工 73-74% 供应宽松，深加工开工提升至 51.2%，成本端及消息面利好支撑。</span></p></td></tr><tr><td colspan=\"1\" rowspan=\"1\" width=\"auto\" style=\"border-width: 1px; border-style: solid; border-color: rgb(204, 204, 204);\"><p style=\"text-align: left;\"><span style=\"font-size: 16px;\">DEG</span></p></td><td colspan=\"1\" rowspan=\"1\" width=\"auto\" style=\"border-width: 1px; border-style: solid; border-color: rgb(204, 204, 204);\"><p style=\"text-align: left;\"><span style=\"font-size: 16px;\">5050</span></p></td><td colspan=\"1\" rowspan=\"1\" width=\"auto\" style=\"border-width: 1px; border-style: solid; border-color: rgb(204, 204, 204);\"><p style=\"text-align: left;\"><span style=\"font-size: 16px;\">0.20%</span></p></td><td colspan=\"1\" rowspan=\"1\" width=\"auto\" style=\"border-width: 1px; border-style: solid; border-color: rgb(204, 204, 204);\"><p style=\"text-align: left;\"><span style=\"font-size: 16px;\">9.90%</span></p></td><td colspan=\"1\" rowspan=\"1\" width=\"auto\" style=\"border-width: 1px; border-style: solid; border-color: rgb(204, 204, 204);\"><p style=\"text-align: left;\"><span style=\"font-size: 16px;\">-7.68%</span></p></td><td colspan=\"1\" rowspan=\"1\" width=\"auto\" style=\"border-width: 1px; border-style: solid; border-color: rgb(204, 204, 204);\"><p style=\"text-align: left;\"><span style=\"font-size: 16px;\">10.87%</span></p></td><td colspan=\"1\" rowspan=\"1\" width=\"auto\" style=\"border-width: 1px; border-style: solid; border-color: rgb(204, 204, 204);\"><p style=\"text-align: left;\"><span style=\"font-size: 16px;\">元 / 吨</span></p></td><td colspan=\"1\" rowspan=\"1\" width=\"auto\" style=\"border-width: 1px; border-style: solid; border-color: rgb(204, 204, 204);\"><p style=\"text-align: left;\"><span style=\"font-size: 16px;\">供需基本面改善，下游聚酯行业需求温和回升。</span></p></td></tr><tr><td colspan=\"1\" rowspan=\"1\" width=\"auto\" style=\"border-width: 1px; border-style: solid; border-color: rgb(204, 204, 204);\"><p style=\"text-align: left;\"><span style=\"font-size: 16px;\">蒽油</span></p></td><td colspan=\"1\" rowspan=\"1\" width=\"auto\" style=\"border-width: 1px; border-style: solid; border-color: rgb(204, 204, 204);\"><p style=\"text-align: left;\"><span style=\"font-size: 16px;\">3554</span></p></td><td colspan=\"1\" rowspan=\"1\" width=\"auto\" style=\"border-width: 1px; border-style: solid; border-color: rgb(204, 204, 204);\"><p style=\"text-align: left;\"><span style=\"font-size: 16px;\">-4.74%</span></p></td><td colspan=\"1\" rowspan=\"1\" width=\"auto\" style=\"border-width: 1px; border-style: solid; border-color: rgb(204, 204, 204);\"><p style=\"text-align: left;\"><span style=\"font-size: 16px;\">9.89%</span></p></td><td colspan=\"1\" rowspan=\"1\" width=\"auto\" style=\"border-width: 1px; border-style: solid; border-color: rgb(204, 204, 204);\"><p style=\"text-align: left;\"><span style=\"font-size: 16px;\">-16.63%</span></p></td><td colspan=\"1\" rowspan=\"1\" width=\"auto\" style=\"border-width: 1px; border-style: solid; border-color: rgb(204, 204, 204);\"><p style=\"text-align: left;\"><span style=\"font-size: 16px;\">-1.17%</span></p></td><td colspan=\"1\" rowspan=\"1\" width=\"auto\" style=\"border-width: 1px; border-style: solid; border-color: rgb(204, 204, 204);\"><p style=\"text-align: left;\"><span style=\"font-size: 16px;\">元 / 吨</span></p></td><td colspan=\"1\" rowspan=\"1\" width=\"auto\" style=\"border-width: 1px; border-style: solid; border-color: rgb(204, 204, 204);\"><p style=\"text-align: left;\"><span style=\"font-size: 16px;\">煤焦油价格上行传导，炭黑市场推涨，下游采买积极性提升但抵触高价。</span></p></td></tr><tr><td colspan=\"1\" rowspan=\"1\" width=\"auto\" style=\"border-width: 1px; border-style: solid; border-color: rgb(204, 204, 204);\"><p style=\"text-align: left;\"><span style=\"font-size: 16px;\">敌草隆</span></p></td><td colspan=\"1\" rowspan=\"1\" width=\"auto\" style=\"border-width: 1px; border-style: solid; border-color: rgb(204, 204, 204);\"><p style=\"text-align: left;\"><span style=\"font-size: 16px;\">34500</span></p></td><td colspan=\"1\" rowspan=\"1\" width=\"auto\" style=\"border-width: 1px; border-style: solid; border-color: rgb(204, 204, 204);\"><p style=\"text-align: left;\"><span style=\"font-size: 16px;\">6.15%</span></p></td><td colspan=\"1\" rowspan=\"1\" width=\"auto\" style=\"border-width: 1px; border-style: solid; border-color: rgb(204, 204, 204);\"><p style=\"text-align: left;\"><span style=\"font-size: 16px;\">9.52%</span></p></td><td colspan=\"1\" rowspan=\"1\" width=\"auto\" style=\"border-width: 1px; border-style: solid; border-color: rgb(204, 204, 204);\"><p style=\"text-align: left;\"><span style=\"font-size: 16px;\">-2.13%</span></p></td><td colspan=\"1\" rowspan=\"1\" width=\"auto\" style=\"border-width: 1px; border-style: solid; border-color: rgb(204, 204, 204);\"><p style=\"text-align: left;\"><span style=\"font-size: 16px;\">6.15%</span></p></td><td colspan=\"1\" rowspan=\"1\" width=\"auto\" style=\"border-width: 1px; border-style: solid; border-color: rgb(204, 204, 204);\"><p style=\"text-align: left;\"><span style=\"font-size: 16px;\">元 / 吨</span></p></td><td colspan=\"1\" rowspan=\"1\" width=\"auto\" style=\"border-width: 1px; border-style: solid; border-color: rgb(204, 204, 204);\"><p style=\"text-align: left;\"><span style=\"font-size: 16px;\">上游原料 3,4 - 二氯苯胺货源偏紧，甲苯价格上涨，成本支撑显著。</span></p></td></tr></tbody></table><h4><span style=\"color: rgb(0, 0, 0); font-size: 16px;\"><strong>2. 跌幅前十产品（2025 年 5 月）</strong></span></h4><table style=\"width: auto;table-layout: fixed;height:2183\"><colgroup contentEditable=\"false\"><col width=90></col><col width=90></col><col width=90></col><col width=90></col><col width=90></col><col width=90></col><col width=90></col><col width=90></col></colgroup><tbody><tr><td colspan=\"1\" rowspan=\"1\" width=\"auto\" style=\"border-width: 1px; border-style: solid; border-color: rgb(204, 204, 204);\"><p style=\"text-align: center;\"><span style=\"font-size: 16px;\"><strong>产品</strong></span></p></td><td colspan=\"1\" rowspan=\"1\" width=\"auto\" style=\"border-width: 1px; border-style: solid; border-color: rgb(204, 204, 204);\"><p style=\"text-align: center;\"><span style=\"font-size: 16px;\"><strong>当前价格</strong></span></p></td><td colspan=\"1\" rowspan=\"1\" width=\"auto\" style=\"border-width: 1px; border-style: solid; border-color: rgb(204, 204, 204);\"><p style=\"text-align: center;\"><span style=\"font-size: 16px;\"><strong>周涨幅</strong></span></p></td><td colspan=\"1\" rowspan=\"1\" width=\"auto\" style=\"border-width: 1px; border-style: solid; border-color: rgb(204, 204, 204);\"><p style=\"text-align: center;\"><span style=\"font-size: 16px;\"><strong>月涨幅</strong></span></p></td><td colspan=\"1\" rowspan=\"1\" width=\"auto\" style=\"border-width: 1px; border-style: solid; border-color: rgb(204, 204, 204);\"><p style=\"text-align: center;\"><span style=\"font-size: 16px;\"><strong>同比</strong></span></p></td><td colspan=\"1\" rowspan=\"1\" width=\"auto\" style=\"border-width: 1px; border-style: solid; border-color: rgb(204, 204, 204);\"><p style=\"text-align: center;\"><span style=\"font-size: 16px;\"><strong>年初至今</strong></span></p></td><td colspan=\"1\" rowspan=\"1\" width=\"auto\" style=\"border-width: 1px; border-style: solid; border-color: rgb(204, 204, 204);\"><p style=\"text-align: center;\"><span style=\"font-size: 16px;\"><strong>单位</strong></span></p></td><td colspan=\"1\" rowspan=\"1\" width=\"auto\" style=\"border-width: 1px; border-style: solid; border-color: rgb(204, 204, 204);\"><p style=\"text-align: center;\"><span style=\"font-size: 16px;\"><strong>市场分析</strong></span></p></td></tr><tr><td colspan=\"1\" rowspan=\"1\" width=\"auto\" style=\"border-width: 1px; border-style: solid; border-color: rgb(204, 204, 204);\"><p style=\"text-align: left;\"><span style=\"font-size: 16px;\">TMA</span></p></td><td colspan=\"1\" rowspan=\"1\" width=\"auto\" style=\"border-width: 1px; border-style: solid; border-color: rgb(204, 204, 204);\"><p style=\"text-align: left;\"><span style=\"font-size: 16px;\">21000</span></p></td><td colspan=\"1\" rowspan=\"1\" width=\"auto\" style=\"border-width: 1px; border-style: solid; border-color: rgb(204, 204, 204);\"><p style=\"text-align: left;\"><span style=\"font-size: 16px;\">-14.29%</span></p></td><td colspan=\"1\" rowspan=\"1\" width=\"auto\" style=\"border-width: 1px; border-style: solid; border-color: rgb(204, 204, 204);\"><p style=\"text-align: left;\"><span style=\"font-size: 16px;\">-36.36%</span></p></td><td colspan=\"1\" rowspan=\"1\" width=\"auto\" style=\"border-width: 1px; border-style: solid; border-color: rgb(204, 204, 204);\"><p style=\"text-align: left;\"><span style=\"font-size: 16px;\">-58.21%</span></p></td><td colspan=\"1\" rowspan=\"1\" width=\"auto\" style=\"border-width: 1px; border-style: solid; border-color: rgb(204, 204, 204);\"><p style=\"text-align: left;\"><span style=\"font-size: 16px;\">-58.82%</span></p></td><td colspan=\"1\" rowspan=\"1\" width=\"auto\" style=\"border-width: 1px; border-style: solid; border-color: rgb(204, 204, 204);\"><p style=\"text-align: left;\"><span style=\"font-size: 16px;\">元 / 吨</span></p></td><td colspan=\"1\" rowspan=\"1\" width=\"auto\" style=\"border-width: 1px; border-style: solid; border-color: rgb(204, 204, 204);\"><p style=\"text-align: left;\"><span style=\"font-size: 16px;\">供需失衡，下游需求疲软，行业产能过剩问题突出。</span></p></td></tr><tr><td colspan=\"1\" rowspan=\"1\" width=\"auto\" style=\"border-width: 1px; border-style: solid; border-color: rgb(204, 204, 204);\"><p style=\"text-align: left;\"><span style=\"font-size: 16px;\">二氯丙烷 - 白料</span></p></td><td colspan=\"1\" rowspan=\"1\" width=\"auto\" style=\"border-width: 1px; border-style: solid; border-color: rgb(204, 204, 204);\"><p style=\"text-align: left;\"><span style=\"font-size: 16px;\">2150</span></p></td><td colspan=\"1\" rowspan=\"1\" width=\"auto\" style=\"border-width: 1px; border-style: solid; border-color: rgb(204, 204, 204);\"><p style=\"text-align: left;\"><span style=\"font-size: 16px;\">-2.27%</span></p></td><td colspan=\"1\" rowspan=\"1\" width=\"auto\" style=\"border-width: 1px; border-style: solid; border-color: rgb(204, 204, 204);\"><p style=\"text-align: left;\"><span style=\"font-size: 16px;\">-22.38%</span></p></td><td colspan=\"1\" rowspan=\"1\" width=\"auto\" style=\"border-width: 1px; border-style: solid; border-color: rgb(204, 204, 204);\"><p style=\"text-align: left;\"><span style=\"font-size: 16px;\">21.54%</span></p></td><td colspan=\"1\" rowspan=\"1\" width=\"auto\" style=\"border-width: 1px; border-style: solid; border-color: rgb(204, 204, 204);\"><p style=\"text-align: left;\"><span style=\"font-size: 16px;\">8.31%</span></p></td><td colspan=\"1\" rowspan=\"1\" width=\"auto\" style=\"border-width: 1px; border-style: solid; border-color: rgb(204, 204, 204);\"><p style=\"text-align: left;\"><span style=\"font-size: 16px;\">元 / 吨</span></p></td><td colspan=\"1\" rowspan=\"1\" width=\"auto\" style=\"border-width: 1px; border-style: solid; border-color: rgb(204, 204, 204);\"><p style=\"text-align: left;\"><span style=\"font-size: 16px;\">需求持续偏弱，终端采购不积极，场内交投清淡。</span></p></td></tr><tr><td colspan=\"1\" rowspan=\"1\" width=\"auto\" style=\"border-width: 1px; border-style: solid; border-color: rgb(204, 204, 204);\"><p style=\"text-align: left;\"><span style=\"font-size: 16px;\">新戊二醇</span></p></td><td colspan=\"1\" rowspan=\"1\" width=\"auto\" style=\"border-width: 1px; border-style: solid; border-color: rgb(204, 204, 204);\"><p style=\"text-align: left;\"><span style=\"font-size: 16px;\">8700</span></p></td><td colspan=\"1\" rowspan=\"1\" width=\"auto\" style=\"border-width: 1px; border-style: solid; border-color: rgb(204, 204, 204);\"><p style=\"text-align: left;\"><span style=\"font-size: 16px;\">-6.45%</span></p></td><td colspan=\"1\" rowspan=\"1\" width=\"auto\" style=\"border-width: 1px; border-style: solid; border-color: rgb(204, 204, 204);\"><p style=\"text-align: left;\"><span style=\"font-size: 16px;\">-22.32%</span></p></td><td colspan=\"1\" rowspan=\"1\" width=\"auto\" style=\"border-width: 1px; border-style: solid; border-color: rgb(204, 204, 204);\"><p style=\"text-align: left;\"><span style=\"font-size: 16px;\">-22.32%</span></p></td><td colspan=\"1\" rowspan=\"1\" width=\"auto\" style=\"border-width: 1px; border-style: solid; border-color: rgb(204, 204, 204);\"><p style=\"text-align: left;\"><span style=\"font-size: 16px;\">-18.69%</span></p></td><td colspan=\"1\" rowspan=\"1\" width=\"auto\" style=\"border-width: 1px; border-style: solid; border-color: rgb(204, 204, 204);\"><p style=\"text-align: left;\"><span style=\"font-size: 16px;\">元 / 吨</span></p></td><td colspan=\"1\" rowspan=\"1\" width=\"auto\" style=\"border-width: 1px; border-style: solid; border-color: rgb(204, 204, 204);\"><p style=\"text-align: left;\"><span style=\"font-size: 16px;\">异丁醛价格疲软，下游采购意愿低迷，市场交投清淡。</span></p></td></tr><tr><td colspan=\"1\" rowspan=\"1\" width=\"auto\" style=\"border-width: 1px; border-style: solid; border-color: rgb(204, 204, 204);\"><p style=\"text-align: left;\"><span style=\"font-size: 16px;\">三氯甲烷</span></p></td><td colspan=\"1\" rowspan=\"1\" width=\"auto\" style=\"border-width: 1px; border-style: solid; border-color: rgb(204, 204, 204);\"><p style=\"text-align: left;\"><span style=\"font-size: 16px;\">2179</span></p></td><td colspan=\"1\" rowspan=\"1\" width=\"auto\" style=\"border-width: 1px; border-style: solid; border-color: rgb(204, 204, 204);\"><p style=\"text-align: left;\"><span style=\"font-size: 16px;\">-2.24%</span></p></td><td colspan=\"1\" rowspan=\"1\" width=\"auto\" style=\"border-width: 1px; border-style: solid; border-color: rgb(204, 204, 204);\"><p style=\"text-align: left;\"><span style=\"font-size: 16px;\">-19.09%</span></p></td><td colspan=\"1\" rowspan=\"1\" width=\"auto\" style=\"border-width: 1px; border-style: solid; border-color: rgb(204, 204, 204);\"><p style=\"text-align: left;\"><span style=\"font-size: 16px;\">-23.54%</span></p></td><td colspan=\"1\" rowspan=\"1\" width=\"auto\" style=\"border-width: 1px; border-style: solid; border-color: rgb(204, 204, 204);\"><p style=\"text-align: left;\"><span style=\"font-size: 16px;\">-5.83%</span></p></td><td colspan=\"1\" rowspan=\"1\" width=\"auto\" style=\"border-width: 1px; border-style: solid; border-color: rgb(204, 204, 204);\"><p style=\"text-align: left;\"><span style=\"font-size: 16px;\">元 / 吨</span></p></td><td colspan=\"1\" rowspan=\"1\" width=\"auto\" style=\"border-width: 1px; border-style: solid; border-color: rgb(204, 204, 204);\"><p style=\"text-align: left;\"><span style=\"font-size: 16px;\">供过于求，厂家库存积压，下游制冷剂需求疲软。</span></p></td></tr><tr><td colspan=\"1\" rowspan=\"1\" width=\"auto\" style=\"border-width: 1px; border-style: solid; border-color: rgb(204, 204, 204);\"><p style=\"text-align: left;\"><span style=\"font-size: 16px;\">甲酸</span></p></td><td colspan=\"1\" rowspan=\"1\" width=\"auto\" style=\"border-width: 1px; border-style: solid; border-color: rgb(204, 204, 204);\"><p style=\"text-align: left;\"><span style=\"font-size: 16px;\">2450</span></p></td><td colspan=\"1\" rowspan=\"1\" width=\"auto\" style=\"border-width: 1px; border-style: solid; border-color: rgb(204, 204, 204);\"><p style=\"text-align: left;\"><span style=\"font-size: 16px;\">6.52%</span></p></td><td colspan=\"1\" rowspan=\"1\" width=\"auto\" style=\"border-width: 1px; border-style: solid; border-color: rgb(204, 204, 204);\"><p style=\"text-align: left;\"><span style=\"font-size: 16px;\">-18.33%</span></p></td><td colspan=\"1\" rowspan=\"1\" width=\"auto\" style=\"border-width: 1px; border-style: solid; border-color: rgb(204, 204, 204);\"><p style=\"text-align: left;\"><span style=\"font-size: 16px;\">2.08%</span></p></td><td colspan=\"1\" rowspan=\"1\" width=\"auto\" style=\"border-width: 1px; border-style: solid; border-color: rgb(204, 204, 204);\"><p style=\"text-align: left;\"><span style=\"font-size: 16px;\">-18.33%</span></p></td><td colspan=\"1\" rowspan=\"1\" width=\"auto\" style=\"border-width: 1px; border-style: solid; border-color: rgb(204, 204, 204);\"><p style=\"text-align: left;\"><span style=\"font-size: 16px;\">元 / 吨</span></p></td><td colspan=\"1\" rowspan=\"1\" width=\"auto\" style=\"border-width: 1px; border-style: solid; border-color: rgb(204, 204, 204);\"><p style=\"text-align: left;\"><span style=\"font-size: 16px;\">五一后企业清库存降价，下游买涨不买跌心态，刚需支撑有限。</span></p></td></tr><tr><td colspan=\"1\" rowspan=\"1\" width=\"auto\" style=\"border-width: 1px; border-style: solid; border-color: rgb(204, 204, 204);\"><p style=\"text-align: left;\"><span style=\"font-size: 16px;\">戊二烯</span></p></td><td colspan=\"1\" rowspan=\"1\" width=\"auto\" style=\"border-width: 1px; border-style: solid; border-color: rgb(204, 204, 204);\"><p style=\"text-align: left;\"><span style=\"font-size: 16px;\">4750</span></p></td><td colspan=\"1\" rowspan=\"1\" width=\"auto\" style=\"border-width: 1px; border-style: solid; border-color: rgb(204, 204, 204);\"><p style=\"text-align: left;\"><span style=\"font-size: 16px;\">-1.45%</span></p></td><td colspan=\"1\" rowspan=\"1\" width=\"auto\" style=\"border-width: 1px; border-style: solid; border-color: rgb(204, 204, 204);\"><p style=\"text-align: left;\"><span style=\"font-size: 16px;\">-17.82%</span></p></td><td colspan=\"1\" rowspan=\"1\" width=\"auto\" style=\"border-width: 1px; border-style: solid; border-color: rgb(204, 204, 204);\"><p style=\"text-align: left;\"><span style=\"font-size: 16px;\">-39.10%</span></p></td><td colspan=\"1\" rowspan=\"1\" width=\"auto\" style=\"border-width: 1px; border-style: solid; border-color: rgb(204, 204, 204);\"><p style=\"text-align: left;\"><span style=\"font-size: 16px;\">-27.59%</span></p></td><td colspan=\"1\" rowspan=\"1\" width=\"auto\" style=\"border-width: 1px; border-style: solid; border-color: rgb(204, 204, 204);\"><p style=\"text-align: left;\"><span style=\"font-size: 16px;\">元 / 吨</span></p></td><td colspan=\"1\" rowspan=\"1\" width=\"auto\" style=\"border-width: 1px; border-style: solid; border-color: rgb(204, 204, 204);\"><p style=\"text-align: left;\"><span style=\"font-size: 16px;\">原料裂解 C5 走弱，下游不饱和树脂需求乏力，供应增量压制价格。</span></p></td></tr><tr><td colspan=\"1\" rowspan=\"1\" width=\"auto\" style=\"border-width: 1px; border-style: solid; border-color: rgb(204, 204, 204);\"><p style=\"text-align: left;\"><span style=\"font-size: 16px;\">四氯乙烯</span></p></td><td colspan=\"1\" rowspan=\"1\" width=\"auto\" style=\"border-width: 1px; border-style: solid; border-color: rgb(204, 204, 204);\"><p style=\"text-align: left;\"><span style=\"font-size: 16px;\">4314</span></p></td><td colspan=\"1\" rowspan=\"1\" width=\"auto\" style=\"border-width: 1px; border-style: solid; border-color: rgb(204, 204, 204);\"><p style=\"text-align: left;\"><span style=\"font-size: 16px;\">-5.73%</span></p></td><td colspan=\"1\" rowspan=\"1\" width=\"auto\" style=\"border-width: 1px; border-style: solid; border-color: rgb(204, 204, 204);\"><p style=\"text-align: left;\"><span style=\"font-size: 16px;\">-15.11%</span></p></td><td colspan=\"1\" rowspan=\"1\" width=\"auto\" style=\"border-width: 1px; border-style: solid; border-color: rgb(204, 204, 204);\"><p style=\"text-align: left;\"><span style=\"font-size: 16px;\">-11.94%</span></p></td><td colspan=\"1\" rowspan=\"1\" width=\"auto\" style=\"border-width: 1px; border-style: solid; border-color: rgb(204, 204, 204);\"><p style=\"text-align: left;\"><span style=\"font-size: 16px;\">-7.76%</span></p></td><td colspan=\"1\" rowspan=\"1\" width=\"auto\" style=\"border-width: 1px; border-style: solid; border-color: rgb(204, 204, 204);\"><p style=\"text-align: left;\"><span style=\"font-size: 16px;\">元 / 吨</span></p></td><td colspan=\"1\" rowspan=\"1\" width=\"auto\" style=\"border-width: 1px; border-style: solid; border-color: rgb(204, 204, 204);\"><p style=\"text-align: left;\"><span style=\"font-size: 16px;\">国内产量增长 + 海外货源到港，制冷剂需求走软，供过于求加剧。</span></p></td></tr><tr><td colspan=\"1\" rowspan=\"1\" width=\"auto\" style=\"border-width: 1px; border-style: solid; border-color: rgb(204, 204, 204);\"><p style=\"text-align: left;\"><span style=\"font-size: 16px;\">一氯甲烷</span></p></td><td colspan=\"1\" rowspan=\"1\" width=\"auto\" style=\"border-width: 1px; border-style: solid; border-color: rgb(204, 204, 204);\"><p style=\"text-align: left;\"><span style=\"font-size: 16px;\">1900</span></p></td><td colspan=\"1\" rowspan=\"1\" width=\"auto\" style=\"border-width: 1px; border-style: solid; border-color: rgb(204, 204, 204);\"><p style=\"text-align: left;\"><span style=\"font-size: 16px;\">-11.63%</span></p></td><td colspan=\"1\" rowspan=\"1\" width=\"auto\" style=\"border-width: 1px; border-style: solid; border-color: rgb(204, 204, 204);\"><p style=\"text-align: left;\"><span style=\"font-size: 16px;\">-13.64%</span></p></td><td colspan=\"1\" rowspan=\"1\" width=\"auto\" style=\"border-width: 1px; border-style: solid; border-color: rgb(204, 204, 204);\"><p style=\"text-align: left;\"><span style=\"font-size: 16px;\">-5.00%</span></p></td><td colspan=\"1\" rowspan=\"1\" width=\"auto\" style=\"border-width: 1px; border-style: solid; border-color: rgb(204, 204, 204);\"><p style=\"text-align: left;\"><span style=\"font-size: 16px;\">-22.45%</span></p></td><td colspan=\"1\" rowspan=\"1\" width=\"auto\" style=\"border-width: 1px; border-style: solid; border-color: rgb(204, 204, 204);\"><p style=\"text-align: left;\"><span style=\"font-size: 16px;\">元 / 吨</span></p></td><td colspan=\"1\" rowspan=\"1\" width=\"auto\" style=\"border-width: 1px; border-style: solid; border-color: rgb(204, 204, 204);\"><p style=\"text-align: left;\"><span style=\"font-size: 16px;\">甲醇价格下跌拖累成本，下游甲基氯硅烷需求疲软，库存压力大。</span></p></td></tr><tr><td colspan=\"1\" rowspan=\"1\" width=\"auto\" style=\"border-width: 1px; border-style: solid; border-color: rgb(204, 204, 204);\"><p style=\"text-align: left;\"><span style=\"font-size: 16px;\">液氯</span></p></td><td colspan=\"1\" rowspan=\"1\" width=\"auto\" style=\"border-width: 1px; border-style: solid; border-color: rgb(204, 204, 204);\"><p style=\"text-align: left;\"><span style=\"font-size: 16px;\">-93</span></p></td><td colspan=\"1\" rowspan=\"1\" width=\"auto\" style=\"border-width: 1px; border-style: solid; border-color: rgb(204, 204, 204);\"><p style=\"text-align: left;\"><span style=\"font-size: 16px;\">21.85%</span></p></td><td colspan=\"1\" rowspan=\"1\" width=\"auto\" style=\"border-width: 1px; border-style: solid; border-color: rgb(204, 204, 204);\"><p style=\"text-align: left;\"><span style=\"font-size: 16px;\">-13.41%</span></p></td><td colspan=\"1\" rowspan=\"1\" width=\"auto\" style=\"border-width: 1px; border-style: solid; border-color: rgb(204, 204, 204);\"><p style=\"text-align: left;\"><span style=\"font-size: 16px;\">-124.87%</span></p></td><td colspan=\"1\" rowspan=\"1\" width=\"auto\" style=\"border-width: 1px; border-style: solid; border-color: rgb(204, 204, 204);\"><p style=\"text-align: left;\"><span style=\"font-size: 16px;\">-181.58%</span></p></td><td colspan=\"1\" rowspan=\"1\" width=\"auto\" style=\"border-width: 1px; border-style: solid; border-color: rgb(204, 204, 204);\"><p style=\"text-align: left;\"><span style=\"font-size: 16px;\">元 / 吨</span></p></td><td colspan=\"1\" rowspan=\"1\" width=\"auto\" style=\"border-width: 1px; border-style: solid; border-color: rgb(204, 204, 204);\"><p style=\"text-align: left;\"><span style=\"font-size: 16px;\">氯碱行业副产品供应过剩，需求端 PVC、环氧丙烷等需求低迷。</span></p></td></tr><tr><td colspan=\"1\" rowspan=\"1\" width=\"auto\" style=\"border-width: 1px; border-style: solid; border-color: rgb(204, 204, 204);\"><p style=\"text-align: left;\"><span style=\"font-size: 16px;\">维生素 VE</span></p></td><td colspan=\"1\" rowspan=\"1\" width=\"auto\" style=\"border-width: 1px; border-style: solid; border-color: rgb(204, 204, 204);\"><p style=\"text-align: left;\"><span style=\"font-size: 16px;\">94</span></p></td><td colspan=\"1\" rowspan=\"1\" width=\"auto\" style=\"border-width: 1px; border-style: solid; border-color: rgb(204, 204, 204);\"><p style=\"text-align: left;\"><span style=\"font-size: 16px;\">-4.08%</span></p></td><td colspan=\"1\" rowspan=\"1\" width=\"auto\" style=\"border-width: 1px; border-style: solid; border-color: rgb(204, 204, 204);\"><p style=\"text-align: left;\"><span style=\"font-size: 16px;\">-11.74%</span></p></td><td colspan=\"1\" rowspan=\"1\" width=\"auto\" style=\"border-width: 1px; border-style: solid; border-color: rgb(204, 204, 204);\"><p style=\"text-align: left;\"><span style=\"font-size: 16px;\">36.23%</span></p></td><td colspan=\"1\" rowspan=\"1\" width=\"auto\" style=\"border-width: 1px; border-style: solid; border-color: rgb(204, 204, 204);\"><p style=\"text-align: left;\"><span style=\"font-size: 16px;\">-29.32%</span></p></td><td colspan=\"1\" rowspan=\"1\" width=\"auto\" style=\"border-width: 1px; border-style: solid; border-color: rgb(204, 204, 204);\"><p style=\"text-align: left;\"><span style=\"font-size: 16px;\">元 / 千克</span></p></td><td colspan=\"1\" rowspan=\"1\" width=\"auto\" style=\"border-width: 1px; border-style: solid; border-color: rgb(204, 204, 204);\"><p style=\"text-align: left;\"><span style=\"font-size: 16px;\">供大于求，下游采购谨慎，贸易商降价抛货，出口市场价格下跌传导至内销。</span></p></td></tr></tbody></table><h3><span style=\"color: rgb(0, 0, 0); font-size: 16px;\"><strong>三、行业资讯</strong></span></h3><h4><span style=\"color: rgb(0, 0, 0); font-size: 16px;\"><strong>1. 赛轮集团全球化布局</strong></span></h4><p><span style=\"color: rgb(0, 0, 0); font-size: 16px;\">· </span><span style=\"color: rgb(0, 0, 0); font-size: 16px;\"><strong>印尼工厂</strong></span><span style=\"color: rgb(0, 0, 0); font-size: 16px;\">：5 月 28 日首条高性能乘用车子午线轮胎下线，东南亚第四座生产基地投产，强化东南亚市场布局。</span></p><p><span style=\"color: rgb(0, 0, 0); font-size: 16px;\">· </span><span style=\"color: rgb(0, 0, 0); font-size: 16px;\"><strong>墨西哥工厂</strong></span><span style=\"color: rgb(0, 0, 0); font-size: 16px;\">：5 月 29 日首条高性能半钢子午线轮胎下线，北美首个智能化生产基地运营，产能辐射美洲市场。</span></p><p><span style=\"color: rgb(0, 0, 0); font-size: 16px;\">· </span><span style=\"color: rgb(0, 0, 0); font-size: 16px;\"><strong>品牌价值</strong></span><span style=\"color: rgb(0, 0, 0); font-size: 16px;\">：2025 年跻身全球轮胎品牌价值榜前十，蝉联中国第一，品牌价值同比增长 13%。</span></p><h4><span style=\"color: rgb(0, 0, 0); font-size: 16px;\"><strong>2. 氮肥行业承压运行</strong></span></h4><p><span style=\"color: rgb(0, 0, 0); font-size: 16px;\">· </span><span style=\"color: rgb(0, 0, 0); font-size: 16px;\"><strong>2024 年数据</strong></span><span style=\"color: rgb(0, 0, 0); font-size: 16px;\">：行业利润总额同比降幅 45.7%，利润率 3.8%（4 年最低）；合成氨、氮肥产量创历史新高。</span></p><p><span style=\"color: rgb(0, 0, 0); font-size: 16px;\">· </span><span style=\"color: rgb(0, 0, 0); font-size: 16px;\"><strong>价格走势</strong></span><span style=\"color: rgb(0, 0, 0); font-size: 16px;\">：2024 年尿素均价 2066 元 / 吨（同比 - 14.6%），2025 年 1 月跌至 1586 元 / 吨，当前稳定在 1863 元 / 吨。</span></p><p><span style=\"color: rgb(0, 0, 0); font-size: 16px;\">· </span><span style=\"color: rgb(0, 0, 0); font-size: 16px;\"><strong>原因</strong></span><span style=\"color: rgb(0, 0, 0); font-size: 16px;\">：煤炭成本低位、供应过剩（新建产能释放）、出口受阻。</span></p><h4><span style=\"color: rgb(0, 0, 0); font-size: 16px;\"><strong>3. 化工行业首个大模型升级</strong></span></h4><p><span style=\"color: rgb(0, 0, 0); font-size: 16px;\">· </span><span style=\"font-size: 16px;\"><strong>智能化工大模型 2.0 Pro</strong></span><span style=\"color: rgb(0, 0, 0); font-size: 16px;\">：5 月 21 日发布，应用于 40 余家企业 / 高校，涵盖催化反应、工艺开发、中试放大、工厂优化四大平台，提升研发效率 30%+。</span></p><h4><span style=\"color: rgb(0, 0, 0); font-size: 16px;\"><strong>4. 中央生态环保督察</strong></span></h4><p><span style=\"color: rgb(0, 0, 0); font-size: 16px;\">· </span><span style=\"color: rgb(0, 0, 0); font-size: 16px;\"><strong>第三轮第四批督察</strong></span><span style=\"color: rgb(0, 0, 0); font-size: 16px;\">：5 月 28 日启动，覆盖山西、内蒙古等 5 省及 3 家央企，聚焦黄河流域生态保护与化工企业绿色转型。</span></p><h3><span style=\"color: rgb(0, 0, 0); font-size: 16px;\"><strong>四、重点产品价格走势</strong></span></h3><h4><span style=\"color: rgb(0, 0, 0); font-size: 16px;\"><strong>1. 能源类</strong></span></h4><p><span style=\"color: rgb(0, 0, 0); font-size: 16px;\">· </span><span style=\"color: rgb(0, 0, 0); font-size: 16px;\"><strong>动力煤</strong></span><span style=\"color: rgb(0, 0, 0); font-size: 16px;\">：</span></p><p><span style=\"color: rgb(0, 0, 0); font-size: 16px;\">· 价格：655 元 / 吨（月跌 3.53%），月均值 667 元 / 吨（同比 - 6.72%）。</span></p><p><span style=\"color: rgb(0, 0, 0); font-size: 16px;\">· </span><span style=\"color: rgb(0, 0, 0); font-size: 16px;\"><strong>天然气</strong></span><span style=\"color: rgb(0, 0, 0); font-size: 16px;\">：</span></p><p><span style=\"color: rgb(0, 0, 0); font-size: 16px;\">· 价格：4326 元 / 吨（月跌 3.03%），月均值 4402 元 / 吨（同比 + 1.32%）。</span></p><p><span style=\"color: rgb(0, 0, 0); font-size: 16px;\">· </span><span style=\"color: rgb(0, 0, 0); font-size: 16px;\"><strong>原油</strong></span><span style=\"color: rgb(0, 0, 0); font-size: 16px;\">：</span></p><p><span style=\"color: rgb(0, 0, 0); font-size: 16px;\">· Brent：63 美元 / 桶（月涨 0.11%），月均值 64 美元 / 桶（同比 - 23.33%）。</span></p><p><span style=\"color: rgb(0, 0, 0); font-size: 16px;\">· WTI：61 美元 / 桶（月涨 0.86%），月均值 61 美元 / 桶（同比 - 22.83%）。</span></p><h4><span style=\"color: rgb(0, 0, 0); font-size: 16px;\"><strong>2. 农化类</strong></span></h4><p><span style=\"color: rgb(0, 0, 0); font-size: 16px;\">· </span><span style=\"color: rgb(0, 0, 0); font-size: 16px;\"><strong>复合肥</strong></span><span style=\"color: rgb(0, 0, 0); font-size: 16px;\">：</span></p><p><span style=\"color: rgb(0, 0, 0); font-size: 16px;\">· 氯基复合肥：2525 元 / 吨（月跌 1.37%），价差 - 298 元 / 吨（月跌 25.00%）。</span></p><p><span style=\"color: rgb(0, 0, 0); font-size: 16px;\">· </span><span style=\"color: rgb(0, 0, 0); font-size: 16px;\"><strong>氯化钾</strong></span><span style=\"color: rgb(0, 0, 0); font-size: 16px;\">：</span></p><p><span style=\"color: rgb(0, 0, 0); font-size: 16px;\">· 价格：2956 元 / 吨（持平），月均值 2956 元 / 吨（同比 + 24.01%）。</span></p><p><span style=\"color: rgb(0, 0, 0); font-size: 16px;\">· </span><span style=\"color: rgb(0, 0, 0); font-size: 16px;\"><strong>尿素</strong></span><span style=\"color: rgb(0, 0, 0); font-size: 16px;\">：</span></p><p><span style=\"color: rgb(0, 0, 0); font-size: 16px;\">· 价格：1863 元 / 吨（月涨 2.19%），价差 515 元 / 吨（月涨 17.05%）。</span></p><p><span style=\"color: rgb(0, 0, 0); font-size: 16px;\">· </span><span style=\"color: rgb(0, 0, 0); font-size: 16px;\"><strong>草甘膦</strong></span><span style=\"color: rgb(0, 0, 0); font-size: 16px;\">：</span></p><p><span style=\"color: rgb(0, 0, 0); font-size: 16px;\">· 价格：23497 元 / 吨（月涨 1.70%），价差 736 元 / 吨（月涨 160.04%）。</span></p><h4><span style=\"color: rgb(0, 0, 0); font-size: 16px;\"><strong>3. 化学纤维类</strong></span></h4><p><span style=\"color: rgb(0, 0, 0); font-size: 16px;\">· </span><span style=\"color: rgb(0, 0, 0); font-size: 16px;\"><strong>PX-PTA - 聚酯</strong></span><span style=\"color: rgb(0, 0, 0); font-size: 16px;\">：</span></p><p><span style=\"color: rgb(0, 0, 0); font-size: 16px;\">· PX：6850 元 / 吨（月涨 0.74%），价差 3533 元 / 吨（月涨 1.33%）。</span></p><p><span style=\"color: rgb(0, 0, 0); font-size: 16px;\">· PTA：4966 元 / 吨（月涨 8.32%），价差 59 元 / 吨（月涨 120.33%）。</span></p><p><span style=\"color: rgb(0, 0, 0); font-size: 16px;\">· 聚酯瓶片：5985 元 / 吨（月涨 4.63%），价差 - 475 元 / 吨（月跌 35.53%）。</span></p><p><span style=\"color: rgb(0, 0, 0); font-size: 16px;\">· </span><span style=\"color: rgb(0, 0, 0); font-size: 16px;\"><strong>涤纶长丝</strong></span><span style=\"color: rgb(0, 0, 0); font-size: 16px;\">：</span></p><p><span style=\"color: rgb(0, 0, 0); font-size: 16px;\">· 价格：7250 元 / 吨（月涨 11.54%），价差 242 元 / 吨（月涨 310.00%）。</span></p><p><span style=\"color: rgb(0, 0, 0); font-size: 16px;\">· </span><span style=\"color: rgb(0, 0, 0); font-size: 16px;\"><strong>粘胶短纤</strong></span><span style=\"color: rgb(0, 0, 0); font-size: 16px;\">：</span></p><p><span style=\"color: rgb(0, 0, 0); font-size: 16px;\">· 价格：13000 元 / 吨（月跌 1.14%），价差 218 元 / 吨（月涨 1535.28%）。</span></p><h4><span style=\"color: rgb(0, 0, 0); font-size: 16px;\"><strong>4. 氯碱及化工原料</strong></span></h4><p><span style=\"color: rgb(0, 0, 0); font-size: 16px;\">· </span><span style=\"color: rgb(0, 0, 0); font-size: 16px;\"><strong>纯碱</strong></span><span style=\"color: rgb(0, 0, 0); font-size: 16px;\">：</span></p><p><span style=\"color: rgb(0, 0, 0); font-size: 16px;\">· 轻碱：1323 元 / 吨（月跌 0.45%），重碱：1465 元 / 吨（月跌 0.14%）。</span></p><p><span style=\"color: rgb(0, 0, 0); font-size: 16px;\">· </span><span style=\"color: rgb(0, 0, 0); font-size: 16px;\"><strong>烧碱</strong></span><span style=\"color: rgb(0, 0, 0); font-size: 16px;\">：</span></p><p><span style=\"color: rgb(0, 0, 0); font-size: 16px;\">· 32% 液碱：971 元 / 吨（月涨 2.90%），价差 374 元 / 吨（月涨 9.03%）。</span></p><p><span style=\"color: rgb(0, 0, 0); font-size: 16px;\">· </span><span style=\"color: rgb(0, 0, 0); font-size: 16px;\"><strong>钛白粉</strong></span><span style=\"color: rgb(0, 0, 0); font-size: 16px;\">：</span></p><p><span style=\"color: rgb(0, 0, 0); font-size: 16px;\">· 价格：14519 元 / 吨（月跌 3.12%），价差 - 1610 元 / 吨（月跌 34.23%）。</span></p><h4><span style=\"color: rgb(0, 0, 0); font-size: 16px;\"><strong>5. 橡胶及轮胎</strong></span></h4><p><span style=\"color: rgb(0, 0, 0); font-size: 16px;\">· </span><span style=\"color: rgb(0, 0, 0); font-size: 16px;\"><strong>天然橡胶</strong></span><span style=\"color: rgb(0, 0, 0); font-size: 16px;\">：</span></p><p><span style=\"color: rgb(0, 0, 0); font-size: 16px;\">· 价格：13308 元 / 吨（月跌 6.99%），月均值 14421 元 / 吨（同比 + 2.73%）。</span></p><p><span style=\"color: rgb(0, 0, 0); font-size: 16px;\">· </span><span style=\"color: rgb(0, 0, 0); font-size: 16px;\"><strong>轮胎开工率</strong></span><span style=\"color: rgb(0, 0, 0); font-size: 16px;\">：</span></p><p><span style=\"color: rgb(0, 0, 0); font-size: 16px;\">· 全钢胎：58.80%（同比 - 0.06pct，环比 - 6.34pct）。</span></p><p><span style=\"color: rgb(0, 0, 0); font-size: 16px;\">· 半钢胎：72.53%（同比 - 6.45pct，环比 - 6.68pct）。</span></p><h4><span style=\"color: rgb(0, 0, 0); font-size: 16px;\"><strong>6. 氟化工</strong></span></h4><p><span style=\"color: rgb(0, 0, 0); font-size: 16px;\">· </span><span style=\"color: rgb(0, 0, 0); font-size: 16px;\"><strong>萤石</strong></span><span style=\"color: rgb(0, 0, 0); font-size: 16px;\">：</span></p><p><span style=\"color: rgb(0, 0, 0); font-size: 16px;\">· 价格：3695 元 / 吨（月跌 4.27%），毛利 1184 元 / 吨（月跌 10.03%）。</span></p><p><span style=\"color: rgb(0, 0, 0); font-size: 16px;\">· </span><span style=\"color: rgb(0, 0, 0); font-size: 16px;\"><strong>氢氟酸</strong></span><span style=\"color: rgb(0, 0, 0); font-size: 16px;\">：</span></p><p><span style=\"color: rgb(0, 0, 0); font-size: 16px;\">· 价格：10646 元 / 吨（月跌 6.07%），毛利 - 98 元 / 吨（月跌 114.36%）。</span></p><p><span style=\"color: rgb(0, 0, 0); font-size: 16px;\">· </span><span style=\"color: rgb(0, 0, 0); font-size: 16px;\"><strong>制冷剂</strong></span><span style=\"color: rgb(0, 0, 0); font-size: 16px;\">：</span></p><p><span style=\"color: rgb(0, 0, 0); font-size: 16px;\">· R32：51000 元 / 吨（月涨 4.08%），价差 34842 元 / 吨（月涨 6.39%）。</span></p><p><span style=\"color: rgb(0, 0, 0); font-size: 16px;\">· R134a：48500 元 / 吨（月涨 2.11%），价差 28517 元 / 吨（月涨 6.46%）。</span></p><h4><span style=\"color: rgb(0, 0, 0); font-size: 16px;\"><strong>7. 食品医药添加剂</strong></span></h4><p><span style=\"color: rgb(0, 0, 0); font-size: 16px;\">· </span><span style=\"color: rgb(0, 0, 0); font-size: 16px;\"><strong>维生素</strong></span><span style=\"color: rgb(0, 0, 0); font-size: 16px;\">：</span></p><p><span style=\"color: rgb(0, 0, 0); font-size: 16px;\">· 维生素 A：65 元 / 公斤（月跌 4.41%，同比 - 21.84%）。</span></p><p><span style=\"color: rgb(0, 0, 0); font-size: 16px;\">· 维生素 E：94 元 / 公斤（月跌 11.74%，同比 + 46.41%）。</span></p><p><span style=\"color: rgb(0, 0, 0); font-size: 16px;\">· </span><span style=\"color: rgb(0, 0, 0); font-size: 16px;\"><strong>甜味剂</strong></span><span style=\"color: rgb(0, 0, 0); font-size: 16px;\">：</span></p><p><span style=\"color: rgb(0, 0, 0); font-size: 16px;\">· 三氯蔗糖：25 万元 / 吨（持平），同比 + 127.27%。</span></p><p><span style=\"color: rgb(0, 0, 0); font-size: 16px;\">· 赤藓糖醇：10500 元 / 吨（持平），同比 - 8.70%。</span></p><h4><span style=\"color: rgb(0, 0, 0); font-size: 16px;\"><strong>8. 聚氨酯</strong></span></h4><p><span style=\"color: rgb(0, 0, 0); font-size: 16px;\">· </span><span style=\"color: rgb(0, 0, 0); font-size: 16px;\"><strong>MDI/TDI</strong></span><span style=\"color: rgb(0, 0, 0); font-size: 16px;\">：</span></p><p><span style=\"color: rgb(0, 0, 0); font-size: 16px;\">· 纯 MDI：17900 元 / 吨（月涨 4.37%），价差 5502 元 / 吨（月涨 20.60%）。</span></p><p><span style=\"color: rgb(0, 0, 0); font-size: 16px;\">· 聚合 MDI：16100 元 / 吨（月涨 7.69%），价差 4827 元 / 吨（月涨 90.92%）。</span></p><p><span style=\"color: rgb(0, 0, 0); font-size: 16px;\">· </span><span style=\"color: rgb(0, 0, 0); font-size: 16px;\"><strong>BDO/PTMEG</strong></span><span style=\"color: rgb(0, 0, 0); font-size: 16px;\">：</span></p><p><span style=\"color: rgb(0, 0, 0); font-size: 16px;\">· BDO：8100 元 / 吨（月涨 1.89%），价差 - 689 元 / 吨（月涨 40.16%）。</span></p><p><span style=\"color: rgb(0, 0, 0); font-size: 16px;\">· PTMEG：12150 元 / 吨（持平），价差 191 元 / 吨（月涨 120.13%）。</span></p><h3><span style=\"color: rgb(0, 0, 0); font-size: 16px;\"><strong>五、风险因素</strong></span></h3><p><span style=\"color: rgb(0, 0, 0); font-size: 16px;\">1. </span><span style=\"color: rgb(0, 0, 0); font-size: 16px;\"><strong>宏观经济风险</strong></span><span style=\"color: rgb(0, 0, 0); font-size: 16px;\">：全球经济增速放缓可能导致化工品需求下降，尤其是出口依赖型产品（如轮胎、农药）。</span></p><p><span style=\"color: rgb(0, 0, 0); font-size: 16px;\">2. </span><span style=\"color: rgb(0, 0, 0); font-size: 16px;\"><strong>成本波动风险</strong></span><span style=\"color: rgb(0, 0, 0); font-size: 16px;\">：原油、煤炭等原材料价格波动可能挤压企业利润，尤其是中游加工环节。</span></p><p><span style=\"color: rgb(0, 0, 0); font-size: 16px;\">3. </span><span style=\"color: rgb(0, 0, 0); font-size: 16px;\"><strong>政策风险</strong></span><span style=\"color: rgb(0, 0, 0); font-size: 16px;\">：环保督察趋严可能导致部分中小产能停产，影响供应；国际贸易摩擦（如关税调整）可能冲击出口市场。</span></p><p><span style=\"color: rgb(0, 0, 0); font-size: 16px;\">4. </span><span style=\"color: rgb(0, 0, 0); font-size: 16px;\"><strong>行业周期风险</strong></span><span style=\"color: rgb(0, 0, 0); font-size: 16px;\">：部分产品（如 MDI、维生素）处于周期下行阶段，价格反弹乏力，库存去化压力大。</span></p>",
    "createdAt": "2025-06-04 15:21:02",
    "updatedAt": "2025-06-12 14:07:42",
    "deletedAt": null,
    "column": {
      "id": 1,
      "name": "全部研报"
    },
    "articleStat": {
      "id": 102,
      "readNum": 5
    },
    "isSaved": false
  }
}